flexistore/__init__.py
flexistore/__main__.py
flexistore/backends/__init__.py
flexistore/backends/aws.py
flexistore/backends/azure.py
flexistore/cli/__init__.py
flexistore/cli/args.py
flexistore/cli/commands.py
flexistore/cli/config.py
flexistore/cli/interface.py
flexistore/cli/main.py
flexistore/cli/utils.py
flexistore/core/__init__.py
flexistore/core/base.py
flexistore/core/config.py
flexistore/core/exceptions.py
flexistore/core/manager.py
flexistore/utils/__init__.py
flexistore/utils/retry.py
flexistore/utils/streaming.py
flexistore/utils/validation.py
flexistore-0.2.0.dist-info/licenses/LICENSE
flexistore-0.2.0.dist-info/METADATA
flexistore-0.2.0.dist-info/WHEEL
flexistore-0.2.0.dist-info/entry_points.txt
flexistore-0.2.0.dist-info/top_level.txt
flexistore-0.2.0.dist-info/RECORD
