Metadata-Version: 2.4
Name: flexistore
Version: 0.2.0
Summary: Cloud-agnostic storage interface with enhanced features and async support
Home-page: https://github.com/prakhara56/FlexiStore
Author: Prakhar Agarwal
Author-email: Prakhar Agarwal <prakhara56@gmail.com>
Maintainer-email: Prakhar Agarwal <prakhara56@gmail.com>
License: MIT
Project-URL: Homepage, https://github.com/prakhara56/FlexiStore
Project-URL: Documentation, https://flexistore.readthedocs.io/
Project-URL: Repository, https://github.com/prakhara56/FlexiStore
Project-URL: Bug Tracker, https://github.com/prakhara56/FlexiStore/issues
Project-URL: Changelog, https://github.com/prakhara56/FlexiStore/blob/main/CHANGELOG.md
Keywords: storage,cloud,azure,aws,s3,blob,async
Classifier: Development Status :: 4 - Beta
Classifier: Intended Audience :: Developers
Classifier: License :: OSI Approved :: MIT License
Classifier: Operating System :: OS Independent
Classifier: Programming Language :: Python :: 3
Classifier: Programming Language :: Python :: 3.8
Classifier: Programming Language :: Python :: 3.9
Classifier: Programming Language :: Python :: 3.10
Classifier: Programming Language :: Python :: 3.11
Classifier: Topic :: Software Development :: Libraries :: Python Modules
Classifier: Topic :: System :: Archiving :: Backup
Classifier: Topic :: System :: Filesystems
Requires-Python: >=3.8
License-File: LICENSE
Requires-Dist: azure-storage-blob>=12.0.0
Requires-Dist: boto3>=1.17.0
Requires-Dist: python-dotenv>=1.0.0
Requires-Dist: aiofiles>=23.0.0
Requires-Dist: aioboto3>=11.0.0
Requires-Dist: cryptography>=40.0.0
Requires-Dist: rich>=13.0.0
Requires-Dist: click>=8.0.0
Provides-Extra: dev
Requires-Dist: pytest>=7.0.0; extra == "dev"
Requires-Dist: pytest-asyncio>=0.21.0; extra == "dev"
Requires-Dist: pytest-cov>=4.0.0; extra == "dev"
Requires-Dist: pytest-mock>=3.10.0; extra == "dev"
Requires-Dist: pytest-xdist>=3.0.0; extra == "dev"
Requires-Dist: black>=23.0.0; extra == "dev"
Requires-Dist: isort>=5.12.0; extra == "dev"
Requires-Dist: flake8>=6.0.0; extra == "dev"
Requires-Dist: mypy>=1.0.0; extra == "dev"
Requires-Dist: pre-commit>=3.0.0; extra == "dev"
Requires-Dist: coverage>=7.0.0; extra == "dev"
Requires-Dist: tox>=4.0.0; extra == "dev"
Provides-Extra: docs
Requires-Dist: sphinx>=6.0.0; extra == "docs"
Requires-Dist: sphinx-rtd-theme>=1.2.0; extra == "docs"
Requires-Dist: sphinx-autodoc-typehints>=1.23.0; extra == "docs"
Provides-Extra: async
Requires-Dist: aioboto3>=11.0.0; extra == "async"
Requires-Dist: aiofiles>=23.0.0; extra == "async"
Provides-Extra: encryption
Requires-Dist: cryptography>=40.0.0; extra == "encryption"
Dynamic: author
Dynamic: home-page
Dynamic: license-file
Dynamic: requires-python
